mcp_server_copilot/__init__.py
mcp_server_copilot/__main__.py
mcp_server_copilot/mcp_connection.py
mcp_server_copilot/retriever.py
mcp_server_copilot/router.py
mcp_server_copilot/schemas.py
mcp_server_copilot/server.py
mcp_server_copilot-0.1.3.dist-info/METADATA
mcp_server_copilot-0.1.3.dist-info/WHEEL
mcp_server_copilot-0.1.3.dist-info/entry_points.txt
mcp_server_copilot-0.1.3.dist-info/top_level.txt
mcp_server_copilot-0.1.3.dist-info/RECORD
